all_models/__init__.py
all_models/main.py
all_models-0.1.dist-info/METADATA
all_models-0.1.dist-info/WHEEL
all_models-0.1.dist-info/top_level.txt
all_models-0.1.dist-info/RECORD
